NodeDebugSanFaSanli/README.md
NodeDebugSanFaSanli/__init__.py
NodeDebugSanFaSanli/__main__.py
NodeDebugSanFaSanli/file.epub
NodeDebugSanFaSanli/index.html
NodeDebugSanFaSanli/css/__init__.py
NodeDebugSanFaSanli/css/annotations.css
NodeDebugSanFaSanli/css/main.css
NodeDebugSanFaSanli/css/normalize.css
NodeDebugSanFaSanli/css/popup.css
NodeDebugSanFaSanli/font/__init__.py
NodeDebugSanFaSanli/font/fontello.eot
NodeDebugSanFaSanli/font/fontello.svg
NodeDebugSanFaSanli/font/fontello.ttf
NodeDebugSanFaSanli/font/fontello.woff
NodeDebugSanFaSanli/img/__init__.py
NodeDebugSanFaSanli/img/annotator-glyph-sprite.png
NodeDebugSanFaSanli/img/annotator-icon-sprite.png
NodeDebugSanFaSanli/img/apple-touch-icon.png
NodeDebugSanFaSanli/img/cancelfullscreen.png
NodeDebugSanFaSanli/img/close.png
NodeDebugSanFaSanli/img/fullscreen.png
NodeDebugSanFaSanli/img/loader.gif
NodeDebugSanFaSanli/img/menu-icon.png
NodeDebugSanFaSanli/img/save.png
NodeDebugSanFaSanli/img/saved.png
NodeDebugSanFaSanli/img/settings-s.png
NodeDebugSanFaSanli/img/settings.png
NodeDebugSanFaSanli/img/star.png
NodeDebugSanFaSanli/js/__init__.py
NodeDebugSanFaSanli/js/epub.js
NodeDebugSanFaSanli/js/epub.min.js
NodeDebugSanFaSanli/js/epub.min.map
NodeDebugSanFaSanli/js/hooks.min.js
NodeDebugSanFaSanli/js/hooks.min.map
NodeDebugSanFaSanli/js/reader.js
NodeDebugSanFaSanli/js/reader.js.map
NodeDebugSanFaSanli/js/reader.min.js
NodeDebugSanFaSanli/js/reader.min.map
NodeDebugSanFaSanli/js/hooks/__init__.py
NodeDebugSanFaSanli/js/hooks/extensions/__init__.py
NodeDebugSanFaSanli/js/hooks/extensions/highlight.js
NodeDebugSanFaSanli/js/libs/__init__.py
NodeDebugSanFaSanli/js/libs/jquery.min.js
NodeDebugSanFaSanli/js/libs/localforage.min.js
NodeDebugSanFaSanli/js/libs/screenfull.js
NodeDebugSanFaSanli/js/libs/screenfull.min.js
NodeDebugSanFaSanli/js/libs/zip.min.js
NodeDebugSanFaSanli/js/plugins/__init__.py
NodeDebugSanFaSanli/js/plugins/hypothesis.js
NodeDebugSanFaSanli/js/plugins/search.js
node_debug_san_fa_sanli-2024.3.1.0.dist-info/METADATA
node_debug_san_fa_sanli-2024.3.1.0.dist-info/WHEEL
node_debug_san_fa_sanli-2024.3.1.0.dist-info/entry_points.txt
node_debug_san_fa_sanli-2024.3.1.0.dist-info/top_level.txt
node_debug_san_fa_sanli-2024.3.1.0.dist-info/RECORD
